jupyterlab_datalogs/__init__.py
jupyterlab_datalogs-0.6.0.data/data/share/jupyter/labextensions/jupyterlab-datalogs/package.json
jupyterlab_datalogs-0.6.0.data/data/share/jupyter/labextensions/jupyterlab-datalogs/schemas/jupyterlab-datalogs/datalogs-load-code-plugin.json
jupyterlab_datalogs-0.6.0.data/data/share/jupyter/labextensions/jupyterlab-datalogs/schemas/jupyterlab-datalogs/package.json.orig
jupyterlab_datalogs-0.6.0.data/data/share/jupyter/labextensions/jupyterlab-datalogs/static/522.d6d0cc38abadefc86e4e.js
jupyterlab_datalogs-0.6.0.data/data/share/jupyter/labextensions/jupyterlab-datalogs/static/remoteEntry.79c6d5f03c8717ae4e2d.js
jupyterlab_datalogs-0.6.0.data/data/share/jupyter/labextensions/jupyterlab-datalogs/static/style.js
jupyterlab_datalogs-0.6.0.data/data/share/jupyter/labextensions/jupyterlab-datalogs/static/third-party-licenses.json
jupyterlab_datalogs-0.6.0.data/data/share/jupyter/labextensions/jupyterlab-datalogs/install.json
jupyterlab_datalogs-0.6.0.dist-info/METADATA
jupyterlab_datalogs-0.6.0.dist-info/WHEEL
jupyterlab_datalogs-0.6.0.dist-info/licenses/LICENSE
jupyterlab_datalogs-0.6.0.dist-info/RECORD
