Metadata-Version: 2.3
Name: jupyterlab-datalogs
Version: 0.6.0
Dynamic: Author
Dynamic: Author-email
Summary: JupyterLab extension for DataLogs.
Project-URL: Homepage, https://github.com/PainterQubits/jupyterlab-datalogs
Project-URL: Repository, https://github.com/PainterQubits/jupyterlab-datalogs
License: BSD 3-Clause License
License-File: LICENSE
Keywords: jupyter,jupyterlab,jupyterlab-extension
Classifier: Framework :: Jupyter
Classifier: Framework :: Jupyter :: JupyterLab
Classifier: Framework :: Jupyter :: JupyterLab :: 4
Classifier: Framework :: Jupyter :: JupyterLab :: Extensions
Classifier: Framework :: Jupyter :: JupyterLab :: Extensions :: Prebuilt
Classifier: License :: OSI Approved :: BSD License
Classifier: Programming Language :: Python
Classifier: Programming Language :: Python :: 3
Classifier: Programming Language :: Python :: 3.9
Classifier: Programming Language :: Python :: 3.10
Classifier: Programming Language :: Python :: 3.11
Classifier: Programming Language :: Python :: 3.12
Requires-Python: >=3.9
Provides-Extra: all
Requires-Dist: datalogs>=0.5.1; extra == 'all'
Requires-Dist: jupyterlab-display-name>=0.2.1; extra == 'all'
Requires-Dist: jupyterlab-open-warning[rtc]>=0.2.0; extra == 'all'
Requires-Dist: jupyterlab-pdf-preview>=0.2.1; extra == 'all'
Requires-Dist: jupyterlab<5,>=4.2.5; extra == 'all'
Requires-Dist: matplotlib<4,>=3.9.2; extra == 'all'
Requires-Dist: numpy<3,>=1.26.4; extra == 'all'
Requires-Dist: xarray>=2024.7.0; extra == 'all'
Provides-Extra: analysis
Requires-Dist: datalogs>=0.5.1; extra == 'analysis'
Requires-Dist: matplotlib<4,>=3.9.2; extra == 'analysis'
Requires-Dist: numpy<3,>=1.26.4; extra == 'analysis'
Requires-Dist: xarray>=2024.7.0; extra == 'analysis'
Provides-Extra: jupyterlab
Requires-Dist: jupyterlab<5,>=4.2.5; extra == 'jupyterlab'
Provides-Extra: plugins
Requires-Dist: jupyterlab-display-name>=0.2.1; extra == 'plugins'
Requires-Dist: jupyterlab-open-warning[rtc]>=0.2.0; extra == 'plugins'
Requires-Dist: jupyterlab-pdf-preview>=0.2.1; extra == 'plugins'
